mantle/__init__.py
mantle/compat.py
mantle/common/RAM.py
mantle/common/ROM.py
mantle/common/__init__.py
mantle/common/arbiter.py
mantle/common/arith.py
mantle/common/barrel.py
mantle/common/cascadedring.py
mantle/common/compare.py
mantle/common/counter.py
mantle/common/counterload.py
mantle/common/countermod.py
mantle/common/decode.py
mantle/common/decoder.py
mantle/common/encoder.py
mantle/common/fulladder.py
mantle/common/halfadder.py
mantle/common/johnson.py
mantle/common/logic.py
mantle/common/operator.py
mantle/common/pipo.py
mantle/common/piso.py
mantle/common/register.py
mantle/common/ring.py
mantle/common/sipo.py
mantle/common/siso.py
mantle/coreir/FF.py
mantle/coreir/LUT.py
mantle/coreir/MUX.py
mantle/coreir/__init__.py
mantle/coreir/arith.py
mantle/coreir/compare.py
mantle/coreir/logic.py
mantle/coreir/memory.py
mantle/coreir/register.py
mantle/coreir/type_helpers.py
mantle/coreir/util.py
mantle/lattice/__init__.py
mantle/lattice/ice40/BUF.py
mantle/lattice/ice40/IO.py
mantle/lattice/ice40/IOB.py
mantle/lattice/ice40/PLB.py
mantle/lattice/ice40/PLL.py
mantle/lattice/ice40/RAMB.py
mantle/lattice/ice40/__init__.py
mantle/lattice/ice40/simulation.py
mantle/lattice/mantle40/BUF.py
mantle/lattice/mantle40/FF.py
mantle/lattice/mantle40/IO.py
mantle/lattice/mantle40/LUT.py
mantle/lattice/mantle40/MUX.py
mantle/lattice/mantle40/__init__.py
mantle/lattice/mantle40/arith.py
mantle/lattice/mantle40/compare.py
mantle/lattice/mantle40/decode.py
mantle/lattice/mantle40/fulladder.py
mantle/lattice/mantle40/halfadder.py
mantle/lattice/mantle40/logic.py
mantle/lattice/mantle40/memory.py
mantle/primitives/__init__.py
mantle/primitives/arith.py
mantle/util/__init__.py
mantle/util/debounce.py
mantle/util/edge.py
mantle/util/pwm.py
mantle/util/quad.py
mantle/util/compressor/__init__.py
mantle/util/compressor/compressor.py
mantle/util/compressor/pop.py
mantle/util/lfsr/__init__.py
mantle/util/lfsr/lfsr.py
mantle-1.0.2.dist-info/METADATA
mantle-1.0.2.dist-info/RECORD
mantle-1.0.2.dist-info/WHEEL
mantle-1.0.2.dist-info/top_level.txt
