Metadata-Version: 2.1
Name: mantle
Version: 1.0.2
Summary: The magma standard library
Home-page: https://github.com/phanrahan/mantle
Maintainer: Lenny Truong
Maintainer-email: lenny@cs.stanford.edu
License: MIT
Platform: UNKNOWN
Requires-Python: >=3.6
Requires-Dist: six
Requires-Dist: fault (>=1.0.*)
Requires-Dist: magma-lang (>=1.0.*)
